dreamtim/__init__.py
dreamtim/calculator.py
dreamtim/statistical_tools.py
dreamtim/test_calculator.py
dreamtim-0.2.2.dist-info/LICENSE
dreamtim-0.2.2.dist-info/WHEEL
dreamtim-0.2.2.dist-info/METADATA
dreamtim-0.2.2.dist-info/RECORD
