Metadata-Version: 2.1
Name: dreamtim
Version: 0.2.2
Summary: This is the package with useful functions for personal usage
Author-email: Timofei Ryko <timofei.ryko@gmail.com>
Requires-Python: >=3.6
Classifier: License :: OSI Approved :: MIT License
Project-URL: Home, https://github.com/dreamtim1/dreamtim
